{
	"name": "ds_lastloaddate",
	"properties": {
		"linkedServiceName": {
			"referenceName": "ls_lastloaddate",
			"type": "LinkedServiceReference"
		},
		"annotations": [],
		"type": "Json",
		"typeProperties": {
			"location": {
				"type": "AzureBlobStorageLocation",
				"fileName": "lastloaddate.json",
				"container": "lastuploaddate"
			}
		},
		"schema": {
			"type": "object",
			"properties": {
				"'LastLoadDate": {
					"type": "string"
				}
			}
		}
	},
	"type": "Microsoft.DataFactory/factories/datasets"
}